dump/__init__.py
dump/config_utils.py
dump/airflow/__init__.py
dump/airflow/airflow_utils.py
dump/airflow/base.py
dump/airflow/chain/binder.py
dump/click_house/__init__.py
dump/click_house/connectors.py
dump/files/__init__.py
dump/files/tmp_util.py
dump/mysql/__init__.py
dump/mysql/connectors.py
dump/mysql/manipulators.py
dump/mysql/table.py
dump/postgres/__init__.py
dump/postgres/connectors.py
dump/postgres/manipulators.py
dump/postgres/table.py
dump/postgres/types_util.py
dump/s3/__init__.py
dump/s3/connectors.py
dump/s3_orc/__init__.py
dump/s3_orc/connectors.py
connector_for_bb-0.0.98.dist-info/METADATA
connector_for_bb-0.0.98.dist-info/WHEEL
connector_for_bb-0.0.98.dist-info/top_level.txt
connector_for_bb-0.0.98.dist-info/RECORD
