Metadata-Version: 2.1
Name: connector-for-bb
Version: 0.0.98
Summary: connector
Home-page: https://github.com/your_username/your_repository
Author: Ivan
Author-email: example@example.com
License: MIT
Platform: UNKNOWN
Classifier: Programming Language :: Python :: 3
Classifier: License :: OSI Approved :: MIT License
Classifier: Operating System :: OS Independent
Requires-Python: >=3.10
Requires-Dist: boto3==1.35.30
Requires-Dist: clickhouse-connect==0.8.6
Requires-Dist: numpy==1.26.0
Requires-Dist: pandas==2.2.2
Requires-Dist: psycopg2-binary==2.9.9
Requires-Dist: tqdm==4.66.5
Provides-Extra: develop
Requires-Dist: black==24.8.0; extra == "develop"
Requires-Dist: coverage==5.5; extra == "develop"
Requires-Dist: flake8==6.0.0; extra == "develop"
Requires-Dist: hypothesis==6.9.2; extra == "develop"
Requires-Dist: isort==5.8.0; extra == "develop"
Requires-Dist: mypy==0.812; extra == "develop"
Requires-Dist: pylint==2.17.4; extra == "develop"
Requires-Dist: pytest==7.3.1; extra == "develop"
Requires-Dist: responses==0.13.2; extra == "develop"
